contrack/__init__.py
contrack/contrack.py
ConTrack-0.3.1.dist-info/AUTHORS.txt
ConTrack-0.3.1.dist-info/LICENSE
ConTrack-0.3.1.dist-info/METADATA
ConTrack-0.3.1.dist-info/WHEEL
ConTrack-0.3.1.dist-info/top_level.txt
ConTrack-0.3.1.dist-info/RECORD
