Metadata-Version: 2.1
Name: ConTrack
Version: 0.3.1
Summary: Contour Tracking of circulation anomalies in Weather and Climate Data.
Home-page: https://github.com/steidani/ConTrack
Author: Daniel Steinfeld
Author-email: daniel.steinfeld@alumni.ethz.ch
License: UNKNOWN
Project-URL: Bug Tracker, https://github.com/steidani/ConTrack/issues
Keywords: data,science,meteorology,climate,atmospheric blocking,troughs and ridges
Platform: UNKNOWN
Classifier: Programming Language :: Python :: 3
Classifier: License :: OSI Approved :: MIT License
Classifier: Operating System :: OS Independent
Classifier: Intended Audience :: Science/Research
Classifier: Topic :: Scientific/Engineering :: Atmospheric Science
Requires-Python: >=3.6
Requires-Dist: xarray
Requires-Dist: scipy
Requires-Dist: pandas
Requires-Dist: numpy
Requires-Dist: netCDF4
